Workbook

Sheet Dashboard
A1: GlobalTools Finance Dashboard PRO
A2: Executive financial view with cash forecast, goals and health indicators.
B4: Revenue YTD | D4: Expenses YTD | F4: Net Profit | H4: Net Margin
B5: =SUMIFS(Transactions!$H:$H,Transactions!$E:$E,"Income",Transactions!$F:$F,"<>Cancelled") | D5: =SUMIFS(Transactions!$H:$H,Transactions!$E:$E,"Expense",Transactions!$F:$F,"<>Cancelled") | F5: =B5-D5 | H5: =IFERROR(F5/B5,0)
B8: Cash Balance | C8: =SUM(Accounts!D3:D100) | D8: 90-Day Ending Cash | E8: ='Cash Flow & Forecast'!M6 | F8: Health Score | G8: ='Financial Health'!B13
B11: PRO modules
B12: Cash Flow | C12: Goals & KPIs | D12: Financial Health
B13: Daily + 90-day forecast | C13: Targets and progress | D13: Risk scorecard
B16: Monthly Performance
B17: Month | C17: Revenue | D17: Expenses | E17: Profit | F17: Margin
B18: ='Monthly Summary'!A3 | C18: ='Monthly Summary'!B3 | D18: ='Monthly Summary'!C3 | E18: ='Monthly Summary'!D3 | F18: ='Monthly Summary'!E3
B19: ='Monthly Summary'!A4 | C19: ='Monthly Summary'!B4 | D19: ='Monthly Summary'!C4 | E19: ='Monthly Summary'!D4 | F19: ='Monthly Summary'!E4
B20: ='Monthly Summary'!A5 | C20: ='Monthly Summary'!B5 | D20: ='Monthly Summary'!C5 | E20: ='Monthly Summary'!D5 | F20: ='Monthly Summary'!E5
B21: ='Monthly Summary'!A6 | C21: ='Monthly Summary'!B6 | D21: ='Monthly Summary'!C6 | E21: ='Monthly Summary'!D6 | F21: ='Monthly Summary'!E6
B22: ='Monthly Summary'!A7 | C22: ='Monthly Summary'!B7 | D22: ='Monthly Summary'!C7 | E22: ='Monthly Summary'!D7 | F22: ='Monthly Summary'!E7
B23: ='Monthly Summary'!A8 | C23: ='Monthly Summary'!B8 | D23: ='Monthly Summary'!C8 | E23: ='Monthly Summary'!D8 | F23: ='Monthly Summary'!E8
B24: ='Monthly Summary'!A9 | C24: ='Monthly Summary'!B9 | D24: ='Monthly Summary'!C9 | E24: ='Monthly Summary'!D9 | F24: ='Monthly Summary'!E9
B25: ='Monthly Summary'!A10 | C25: ='Monthly Summary'!B10 | D25: ='Monthly Summary'!C10 | E25: ='Monthly Summary'!D10 | F25: ='Monthly Summary'!E10
B26: ='Monthly Summary'!A11 | C26: ='Monthly Summary'!B11 | D26: ='Monthly Summary'!C11 | E26: ='Monthly Summary'!D11 | F26: ='Monthly Summary'!E11
B27: ='Monthly Summary'!A12 | C27: ='Monthly Summary'!B12 | D27: ='Monthly Summary'!C12 | E27: ='Monthly Summary'!D12 | F27: ='Monthly Summary'!E12
B28: ='Monthly Summary'!A13 | C28: ='Monthly Summary'!B13 | D28: ='Monthly Summary'!C13 | E28: ='Monthly Summary'!D13 | F28: ='Monthly Summary'!E13
B29: ='Monthly Summary'!A14 | C29: ='Monthly Summary'!B14 | D29: ='Monthly Summary'!C14 | E29: ='Monthly Summary'!D14 | F29: ='Monthly Summary'!E14

Sheet Start Here
A1: GlobalTools Finance Dashboard PRO
A2: Professional finance management workbook for small businesses and freelancers.
A4: 1 | B4: Settings | C4: Set business name, targets, forecast start date and cash reserve.
A5: 2 | B5: Transactions | C5: Record income, expenses and cash movements.
A6: 3 | B6: Dashboard | C6: Review KPIs and monthly performance.
A7: 4 | B7: Cash Flow & Forecast | C7: See daily cash and a 90-day projection.
A8: 5 | B8: Goals & KPIs | C8: Track financial targets and progress.
A9: 6 | B9: Financial Health | C9: Review liquidity, profitability and risk indicators.
A10: 7 | B10: Receivables / Payables | C10: Control money owed to you and money you owe.
A11: 8 | B11: Budget / P&L | C11: Plan and compare actual performance.
A14: Important | B14: This is a management planning tool, not accounting or tax advice.

Sheet Settings
A1: Settings
A2: Customize the workbook before using it.
A4: Business Name | B4: Your Business
A5: Owner / Manager | B5: Your Name
A6: Base Currency | B6: USD
A7: Fiscal Year | B7: 2026
A8: Opening Cash | B8: 10000
A9: Target Monthly Revenue | B9: 15000
A10: Target Net Margin | B10: 0.2
A11: Forecast Start Date | B11: 46296
A12: Cash Reserve Target | B12: 5000

Sheet Categories
A1: Categories
A2: Edit categories used across the workbook.
A4: Category | B4: Type | C4: Group | D4: Active
A5: Sales Revenue | B5: Income | C5: Revenue | D5: Yes
A6: Services Revenue | B6: Income | C6: Revenue | D6: Yes
A7: Other Income | B7: Income | C7: Other | D7: Yes
A8: Payroll | B8: Expense | C8: People | D8: Yes
A9: Rent & Utilities | B9: Expense | C9: Operating | D9: Yes
A10: Software & Subscriptions | B10: Expense | C10: Operating | D10: Yes
A11: Marketing | B11: Expense | C11: Operating | D11: Yes
A12: Office & Supplies | B12: Expense | C12: Operating | D12: Yes
A13: Travel | B13: Expense | C13: Operating | D13: Yes
A14: Professional Services | B14: Expense | C14: Operating | D14: Yes
A15: Bank Fees | B15: Expense | C15: Finance | D15: Yes
... A18: Other Expense | B18: Expense | C18: Other | D18: Yes

Sheet Accounts
A1: Accounts
A2: Bank, cash, credit card and wallet balances.
A3: Main Checking | B3: Bank | C3: 8000 | D3: =C3+SUMIFS(Transactions!$H:$H,Transactions!$G:$G,A3,Transactions!$E:$E,"Income")-SUMIFS(Transactions!$H:$H,Transactions!$G:$G,A3,Transactions!$E:$E,"Expense") | E3: Yes
A4: Business Savings | B4: Bank | C4: 2000 | D4: =C4+SUMIFS(Transactions!$H:$H,Transactions!$G:$G,A4,Transactions!$E:$E,"Income")-SUMIFS(Transactions!$H:$H,Transactions!$G:$G,A4,Transactions!$E:$E,"Expense") | E4: Yes
A5: Cash | B5: Cash | C5: 500 | D5: =C5+SUMIFS(Transactions!$H:$H,Transactions!$G:$G,A5,Transactions!$E:$E,"Income")-SUMIFS(Transactions!$H:$H,Transactions!$G:$G,A5,Transactions!$E:$E,"Expense") | E5: Yes
A6: Business Credit Card | B6: Credit Card | C6: 0 | D6: =C6+SUMIFS(Transactions!$H:$H,Transactions!$G:$G,A6,Transactions!$E:$E,"Income")-SUMIFS(Transactions!$H:$H,Transactions!$G:$G,A6,Transactions!$E:$E,"Expense") | E6: Yes

Sheet Customers
A1: Customers
A2: Customer directory.
A4: Customer ID | B4: Customer | C4: Email | D4: Phone | E4: Status | F4: Notes
A5: C-001 | B5: Acme Consulting | C5: billing@acme.example | D5: +1 555-0101 | E5: Active | F5: Monthly consulting
A6: C-002 | B6: Northstar Studio | C6: finance@northstar.example | D6: +1 555-0102 | E6: Active | F6: Design services
A7: C-003 | B7: Greenline Retail | C7: accounts@greenline.example | D7: +1 555-0103 | E7: Active | F7: Retail account
A8: C-004 | B8: BrightPath LLC | C8: ap@brightpath.example | D8: +1 555-0104 | E8: Active | F8: Project client

Sheet Products
A1: Products & Services
A2: Maintain your catalog and pricing.
A3: SVC-001 | B3: Consulting Package | C3: Service | D3: 1500 | E3: 500 | F3: =IFERROR((D3-E3)/D3,0) | G3: Yes
A4: SVC-002 | B4: Monthly Retainer | C4: Service | D4: 1200 | E4: 350 | F4: =IFERROR((D4-E4)/D4,0) | G4: Yes
A5: PRD-001 | B5: Digital Template | C5: Product | D5: 49 | E5: 5 | F5: =IFERROR((D5-E5)/D5,0) | G5: Yes
A6: SVC-003 | B6: Implementation Project | C6: Service | D6: 3000 | E6: 1200 | F6: =IFERROR((D6-E6)/D6,0) | G6: Yes

Sheet Transactions
A1: Transactions
A2: Record all income and expenses using positive amounts.
A4: Date | B4: Reference | C4: Description | D4: Category | E4: Type | F4: Status | G4: Account | H4: Amount | I4: Customer / Vendor | J4: Recurring | K4: Notes
A5: 46027 | B5: INV-1001 | C5: Consulting Package | D5: Services Revenue | E5: Income | F5: Paid | G5: Main Checking | H5: 1500 | I5: Acme Consulting | J5: No | K5: January project
A6: 46030 | B6: BILL-2001 | C6: Software subscription | D6: Software & Subscriptions | E6: Expense | F6: Paid | G6: Main Checking | H6: 99 | I6: Cloud Software | J6: Yes | K6: Monthly
A7: 46034 | B7: INV-1002 | C7: Monthly Retainer | D7: Services Revenue | E7: Income | F7: Paid | G7: Main Checking | H7: 1200 | I7: Northstar Studio | J7: Yes | K7: Retainer
A8: 46042 | B8: BILL-2002 | C8: Marketing campaign | D8: Marketing | E8: Expense | F8: Paid | G8: Business Credit Card | H8: 450 | I8: Ad Platform | J8: No | K8: Campaign
A9: 46056 | B9: INV-1003 | C9: Implementation Project | D9: Services Revenue | E9: Income | F9: Paid | G9: Main Checking | H9: 3000 | I9: BrightPath LLC | J9: No | K9: Phase 1
A10: 46060 | B10: BILL-2003 | C10: Professional services | D10: Professional Services | E10: Expense | F10: Paid | G10: Main Checking | H10: 600 | I10: Accountant | J10: No | K10: Bookkeeping
A11: 46068 | B11: INV-1004 | C11: Digital Template | D11: Sales Revenue | E11: Income | F11: Paid | G11: Main Checking | H11: 49 | I11: Greenline Retail | J11: No | K11: Online sale

Sheet Budget
A1: Budget Planner
A2: Set targets and compare actual results.
A3: 46023 | B3: 15000 | C3: 9000 | D3: =B3-C3 | E3: =SUMIFS(Transactions!$H:$H,Transactions!$A:$A,">="&A3,Transactions!$A:$A,"<"&EDATE(A3,1),Transactions!$E:$E,"Income",Transactions!$F:$F,"<>Cancelled") | F3: =SUMIFS(Transactions!$H:$H,Transactions!$A:$A,">="&A3,Transactions!$A:$A,"<"&EDATE(A3,1),Transactions!$E:$E,"Expense",Transactions!$F:$F,"<>Cancelled") | G3: =E3-F3 | H3: =E3-B3 | I3: =F3-C3 | J3: =G3-D3
A4: 46054 | B4: 15000 | C4: 9000 | D4: =B4-C4 | E4: =SUMIFS(Transactions!$H:$H,Transactions!$A:$A,">="&A4,Transactions!$A:$A,"<"&EDATE(A4,1),Transactions!$E:$E,"Income",Transactions!$F:$F,"<>Cancelled") | F4: =SUMIFS(Transactions!$H:$H,Transactions!$A:$A,">="&A4,Transactions!$A:$A,"<"&EDATE(A4,1),Transactions!$E:$E,"Expense",Transactions!$F:$F,"<>Cancelled") | G4: =E4-F4 | H4: =E4-B4 | I4: =F4-C4 | J4: =G4-D4
A5: 46082 | B5: 15000 | C5: 9000 | D5: =B5-C5 | E5: =SUMIFS(Transactions!$H:$H,Transactions!$A:$A,">="&A5,Transactions!$A:$A,"<"&EDATE(A5,1),Transactions!$E:$E,"Income",Transactions!$F:$F,"<>Cancelled") | F5: =SUMIFS(Transactions!$H:$H,Transactions!$A:$A,">="&A5,Transactions!$A:$A,"<"&EDATE(A5,1),Transactions!$E:$E,"Expense",Transactions!$F:$F,"<>Cancelled") | G5: =E5-F5 | H5: =E5-B5 | I5: =F5-C5 | J5: =G5-D5
A6: 46113 | B6: 15000 | C6: 9000 | D6: =B6-C6 | E6: =SUMIFS(Transactions!$H:$H,Transactions!$A:$A,">="&A6,Transactions!$A:$A,"<"&EDATE(A6,1),Transactions!$E:$E,"Income",Transactions!$F:$F,"<>Cancelled") | F6: =SUMIFS(Transactions!$H:$H,Transactions!$A:$A,">="&A6,Transactions!$A:$A,"<"&EDATE(A6,1),Transactions!$E:$E,"Expense",Transactions!$F:$F,"<>Cancelled") | G6: =E6-F6 | H6: =E6-B6 | I6: =F6-C6 | J6: =G6-D6
A7: 46143 | B7: 15000 | C7: 9000 | D7: =B7-C7 | E7: =SUMIFS(Transactions!$H:$H,Transactions!$A:$A,">="&A7,Transactions!$A:$A,"<"&EDATE(A7,1),Transactions!$E:$E,"Income",Transactions!$F:$F,"<>Cancelled") | F7: =SUMIFS(Transactions!$H:$H,Transactions!$A:$A,">="&A7,Transactions!$A:$A,"<"&EDATE(A7,1),Transactions!$E:$E,"Expense",Transactions!$F:$F,"<>Cancelled") | G7: =E7-F7 | H7: =E7-B7 | I7: =F7-C7 | J7: =G7-D7
A8: 46174 | B8: 15000 | C8: 9000 | D8: =B8-C8 | E8: =SUMIFS(Transactions!$H:$H,Transactions!$A:$A,">="&A8,Transactions!$A:$A,"<"&EDATE(A8,1),Transactions!$E:$E,"Income",Transactions!$F:$F,"<>Cancelled") | F8: =SUMIFS(Transactions!$H:$H,Transactions!$A:$A,">="&A8,Transactions!$A:$A,"<"&EDATE(A8,1),Transactions!$E:$E,"Expense",Transactions!$F:$F,"<>Cancelled") | G8: =E8-F8 | H8: =E8-B8 | I8: =F8-C8 | J8: =G8-D8
A9: 46204 | B9: 15000 | C9: 9000 | D9: =B9-C9 | E9: =SUMIFS(Transactions!$H:$H,Transactions!$A:$A,">="&A9,Transactions!$A:$A,"<"&EDATE(A9,1),Transactions!$E:$E,"Income",Transactions!$F:$F,"<>Cancelled") | F9: =SUMIFS(Transactions!$H:$H,Transactions!$A:$A,">="&A9,Transactions!$A:$A,"<"&EDATE(A9,1),Transactions!$E:$E,"Expense",Transactions!$F:$F,"<>Cancelled") | G9: =E9-F9 | H9: =E9-B9 | I9: =F9-C9 | J9: =G9-D9
A10: 46235 | B10: 15000 | C10: 9000 | D10: =B10-C10 | E10: =SUMIFS(Transactions!$H:$H,Transactions!$A:$A,">="&A10,Transactions!$A:$A,"<"&EDATE(A10,1),Transactions!$E:$E,"Income",Transactions!$F:$F,"<>Cancelled") | F10: =SUMIFS(Transactions!$H:$H,Transactions!$A:$A,">="&A10,Transactions!$A:$A,"<"&EDATE(A10,1),Transactions!$E:$E,"Expense",Transactions!$F:$F,"<>Cancelled") | G10: =E10-F10 | H10: =E10-B10 | I10: =F10-C10 | J10: =G10-D10
A11: 46266 | B11: 15000 | C11: 9000 | D11: =B11-C11 | E11: =SUMIFS(Transactions!$H:$H,Transactions!$A:$A,">="&A11,Transactions!$A:$A,"<"&EDATE(A11,1),Transactions!$E:$E,"Income",Transactions!$F:$F,"<>Cancelled") | F11: =SUMIFS(Transactions!$H:$H,Transactions!$A:$A,">="&A11,Transactions!$A:$A,"<"&EDATE(A11,1),Transactions!$E:$E,"Expense",Transactions!$F:$F,"<>Cancelled") | G11: =E11-F11 | H11: =E11-B11 | I11: =F11-C11 | J11: =G11-D11
A12: 46296 | B12: 15000 | C12: 9000 | D12: =B12-C12 | E12: =SUMIFS(Transactions!$H:$H,Transactions!$A:$A,">="&A12,Transactions!$A:$A,"<"&EDATE(A12,1),Transactions!$E:$E,"Income",Transactions!$F:$F,"<>Cancelled") | F12: =SUMIFS(Transactions!$H:$H,Transactions!$A:$A,">="&A12,Transactions!$A:$A,"<"&EDATE(A12,1),Transactions!$E:$E,"Expense",Transactions!$F:$F,"<>Cancelled") | G12: =E12-F12 | H12: =E12-B12 | I12: =F12-C12 | J12: =G12-D12
A13: 46327 | B13: 15000 | C13: 9000 | D13: =B13-C13 | E13: =SUMIFS(Transactions!$H:$H,Transactions!$A:$A,">="&A13,Transactions!$A:$A,"<"&EDATE(A13,1),Transactions!$E:$E,"Income",Transactions!$F:$F,"<>Cancelled") | F13: =SUMIFS(Transactions!$H:$H,Transactions!$A:$A,">="&A13,Transactions!$A:$A,"<"&EDATE(A13,1),Transactions!$E:$E,"Expense",Transactions!$F:$F,"<>Cancelled") | G13: =E13-F13 | H13: =E13-B13 | I13: =F13-C13 | J13: =G13-D13
A14: 46357 | B14: 15000 | C14: 9000 | D14: =B14-C14 | E14: =SUMIFS(Transactions!$H:$H,Transactions!$A:$A,">="&A14,Transactions!$A:$A,"<"&EDATE(A14,1),Transactions!$E:$E,"Income",Transactions!$F:$F,"<>Cancelled") | F14: =SUMIFS(Transactions!$H:$H,Transactions!$A:$A,">="&A14,Transactions!$A:$A,"<"&EDATE(A14,1),Transactions!$E:$E,"Expense",Transactions!$F:$F,"<>Cancelled") | G14: =E14-F14 | H14: =E14-B14 | I14: =F14-C14 | J14: =G14-D14

Sheet Monthly Summary
A1: Monthly Financial Summary
A2: Revenue, expenses, profit, margin, budget variance and cumulative profit.
A3: 46023 | B3: =Budget!E3 | C3: =Budget!F3 | D3: =B3-C3 | E3: =IFERROR(D3/B3,0) | F3: =Budget!B3 | G3: =Budget!C3 | H3: =Budget!D3 | I3: =B3-F3 | J3: =C3-G3 | K3: =D3-H3 | L3: =SUM($D$3:D3)
A4: 46054 | B4: =Budget!E4 | C4: =Budget!F4 | D4: =B4-C4 | E4: =IFERROR(D4/B4,0) | F4: =Budget!B4 | G4: =Budget!C4 | H4: =Budget!D4 | I4: =B4-F4 | J4: =C4-G4 | K4: =D4-H4 | L4: =SUM($D$3:D4)
A5: 46082 | B5: =Budget!E5 | C5: =Budget!F5 | D5: =B5-C5 | E5: =IFERROR(D5/B5,0) | F5: =Budget!B5 | G5: =Budget!C5 | H5: =Budget!D5 | I5: =B5-F5 | J5: =C5-G5 | K5: =D5-H5 | L5: =SUM($D$3:D5)
A6: 46113 | B6: =Budget!E6 | C6: =Budget!F6 | D6: =B6-C6 | E6: =IFERROR(D6/B6,0) | F6: =Budget!B6 | G6: =Budget!C6 | H6: =Budget!D6 | I6: =B6-F6 | J6: =C6-G6 | K6: =D6-H6 | L6: =SUM($D$3:D6)
A7: 46143 | B7: =Budget!E7 | C7: =Budget!F7 | D7: =B7-C7 | E7: =IFERROR(D7/B7,0) | F7: =Budget!B7 | G7: =Budget!C7 | H7: =Budget!D7 | I7: =B7-F7 | J7: =C7-G7 | K7: =D7-H7 | L7: =SUM($D$3:D7)
A8: 46174 | B8: =Budget!E8 | C8: =Budget!F8 | D8: =B8-C8 | E8: =IFERROR(D8/B8,0) | F8: =Budget!B8 | G8: =Budget!C8 | H8: =Budget!D8 | I8: =B8-F8 | J8: =C8-G8 | K8: =D8-H8 | L8: =SUM($D$3:D8)
A9: 46204 | B9: =Budget!E9 | C9: =Budget!F9 | D9: =B9-C9 | E9: =IFERROR(D9/B9,0) | F9: =Budget!B9 | G9: =Budget!C9 | H9: =Budget!D9 | I9: =B9-F9 | J9: =C9-G9 | K9: =D9-H9 | L9: =SUM($D$3:D9)
A10: 46235 | B10: =Budget!E10 | C10: =Budget!F10 | D10: =B10-C10 | E10: =IFERROR(D10/B10,0) | F10: =Budget!B10 | G10: =Budget!C10 | H10: =Budget!D10 | I10: =B10-F10 | J10: =C10-G10 | K10: =D10-H10 | L10: =SUM($D$3:D10)
A11: 46266 | B11: =Budget!E11 | C11: =Budget!F11 | D11: =B11-C11 | E11: =IFERROR(D11/B11,0) | F11: =Budget!B11 | G11: =Budget!C11 | H11: =Budget!D11 | I11: =B11-F11 | J11: =C11-G11 | K11: =D11-H11 | L11: =SUM($D$3:D11)
A12: 46296 | B12: =Budget!E12 | C12: =Budget!F12 | D12: =B12-C12 | E12: =IFERROR(D12/B12,0) | F12: =Budget!B12 | G12: =Budget!C12 | H12: =Budget!D12 | I12: =B12-F12 | J12: =C12-G12 | K12: =D12-H12 | L12: =SUM($D$3:D12)
A13: 46327 | B13: =Budget!E13 | C13: =Budget!F13 | D13: =B13-C13 | E13: =IFERROR(D13/B13,0) | F13: =Budget!B13 | G13: =Budget!C13 | H13: =Budget!D13 | I13: =B13-F13 | J13: =C13-G13 | K13: =D13-H13 | L13: =SUM($D$3:D13)
A14: 46357 | B14: =Budget!E14 | C14: =Budget!F14 | D14: =B14-C14 | E14: =IFERROR(D14/B14,0) | F14: =Budget!B14 | G14: =Budget!C14 | H14: =Budget!D14 | I14: =B14-F14 | J14: =C14-G14 | K14: =D14-H14 | L14: =SUM($D$3:D14)

Sheet Receivables
A1: Accounts Receivable
A2: Track invoices, collections and aging.
A3: INV-1005 | B3: Acme Consulting | C3: 46082 | D3: 46112 | E3: 1800 | F3: 0 | G3: =E3-F3 | I3: =IF(OR(G3=0,H3="Paid"),0,MAX(0,TODAY()-D3))
A4: INV-1006 | B4: Northstar Studio | C4: 46086 | D4: 46101 | E4: 1200 | F4: 600 | G4: =E4-F4 | H4: Status | I4: =IF(OR(G4=0,H4="Paid"),0,MAX(0,TODAY()-D4)) | J4: Notes
A5: INV-1007 | B5: BrightPath LLC | C5: 46091 | D5: 46122 | E5: 3000 | F5: 0 | G5: =E5-F5 | I5: =IF(OR(G5=0,H5="Paid"),0,MAX(0,TODAY()-D5))
A6: INV-1008 | B6: Greenline Retail | C6: 46093 | D6: 46106 | E6: 750 | F6: 750 | G6: =E6-F6 | I6: =IF(OR(G6=0,H6="Paid"),0,MAX(0,TODAY()-D6))

Sheet Payables
A1: Accounts Payable
A2: Track supplier bills and upcoming obligations.
A3: BILL-3001 | B3: Cloud Software | C3: 46082 | D3: 46096 | E3: 99 | F3: 99 | G3: =E3-F3 | H3: Normal | I3: =IF(OR(G3=0,H3="Paid"),0,MAX(0,TODAY()-D3))
A4: BILL-3002 | B4: Ad Platform | C4: 46086 | D4: 46099 | E4: 450 | F4: 0 | G4: =E4-F4 | H4: High | I4: =IF(OR(G4=0,H4="Paid"),0,MAX(0,TODAY()-D4)) | J4: Priority
A5: BILL-3003 | B5: Accountant | C5: 46091 | D5: 46111 | E5: 600 | F5: 0 | G5: =E5-F5 | H5: Medium | I5: =IF(OR(G5=0,H5="Paid"),0,MAX(0,TODAY()-D5))
A6: BILL-3004 | B6: Office Supplier | C6: 46093 | D6: 46117 | E6: 320 | F6: 0 | G6: =E6-F6 | H6: Normal | I6: =IF(OR(G6=0,H6="Paid"),0,MAX(0,TODAY()-D6))

Sheet P&L Statement
A1: Profit & Loss Statement
A2: Management P&L derived from Transactions.
A3: Revenue | B3: =SUMIFS(Transactions!$H:$H,Transactions!$A:$A,">="&DATE(2026,1,1),Transactions!$A:$A,"<"&EDATE(DATE(2026,1,1),1),Transactions!$E:$E,"Income",Transactions!$F:$F,"<>Cancelled") | C3: =SUMIFS(Transactions!$H:$H,Transactions!$A:$A,">="&DATE(2026,2,1),Transactions!$A:$A,"<"&EDATE(DATE(2026,2,1),1),Transactions!$E:$E,"Income",Transactions!$F:$F,"<>Cancelled") | D3: =SUMIFS(Transactions!$H:$H,Transactions!$A:$A,">="&DATE(2026,3,1),Transactions!$A:$A,"<"&EDATE(DATE(2026,3,1),1),Transactions!$E:$E,"Income",Transactions!$F:$F,"<>Cancelled") | E3: =SUMIFS(Transactions!$H:$H,Transactions!$A:$A,">="&DATE(2026,4,1),Transactions!$A:$A,"<"&EDATE(DATE(2026,4,1),1),Transactions!$E:$E,"Income",Transactions!$F:$F,"<>Cancelled") | F3: =SUMIFS(Transactions!$H:$H,Transactions!$A:$A,">="&DATE(2026,5,1),Transactions!$A:$A,"<"&EDATE(DATE(2026,5,1),1),Transactions!$E:$E,"Income",Transactions!$F:$F,"<>Cancelled") | G3: =SUMIFS(Transactions!$H:$H,Transactions!$A:$A,">="&DATE(2026,6,1),Transactions!$A:$A,"<"&EDATE(DATE(2026,6,1),1),Transactions!$E:$E,"Income",Transactions!$F:$F,"<>Cancelled") | H3: =SUMIFS(Transactions!$H:$H,Transactions!$A:$A,">="&DATE(2026,7,1),Transactions!$A:$A,"<"&EDATE(DATE(2026,7,1),1),Transactions!$E:$E,"Income",Transactions!$F:$F,"<>Cancelled") | I3: =SUMIFS(Transactions!$H:$H,Transactions!$A:$A,">="&DATE(2026,8,1),Transactions!$A:$A,"<"&EDATE(DATE(2026,8,1),1),Transactions!$E:$E,"Income",Transactions!$F:$F,"<>Cancelled") | J3: =SUMIFS(Transactions!$H:$H,Transactions!$A:$A,">="&DATE(2026,9,1),Transactions!$A:$A,"<"&EDATE(DATE(2026,9,1),1),Transactions!$E:$E,"Income",Transactions!$F:$F,"<>Cancelled") | K3: =SUMIFS(Transactions!$H:$H,Transactions!$A:$A,">="&DATE(2026,10,1),Transactions!$A:$A,"<"&EDATE(DATE(2026,10,1),1),Transactions!$E:$E,"Income",Transactions!$F:$F,"<>Cancelled") | L3: =SUMIFS(Transactions!$H:$H,Transactions!$A:$A,">="&DATE(2026,11,1),Transactions!$A:$A,"<"&EDATE(DATE(2026,11,1),1),Transactions!$E:$E,"Income",Transactions!$F:$F,"<>Cancelled") | M3: =SUMIFS(Transactions!$H:$H,Transactions!$A:$A,">="&DATE(2026,12,1),Transactions!$A:$A,"<"&EDATE(DATE(2026,12,1),1),Transactions!$E:$E,"Income",Transactions!$F:$F,"<>Cancelled") | N3: =SUM(B3:M3)
A4: Operating Expenses | B4: =SUMIFS(Transactions!$H:$H,Transactions!$A:$A,">="&DATE(2026,1,1),Transactions!$A:$A,"<"&EDATE(DATE(2026,1,1),1),Transactions!$E:$E,"Expense",Transactions!$F:$F,"<>Cancelled") | C4: =SUMIFS(Transactions!$H:$H,Transactions!$A:$A,">="&DATE(2026,2,1),Transactions!$A:$A,"<"&EDATE(DATE(2026,2,1),1),Transactions!$E:$E,"Expense",Transactions!$F:$F,"<>Cancelled") | D4: =SUMIFS(Transactions!$H:$H,Transactions!$A:$A,">="&DATE(2026,3,1),Transactions!$A:$A,"<"&EDATE(DATE(2026,3,1),1),Transactions!$E:$E,"Expense",Transactions!$F:$F,"<>Cancelled") | E4: =SUMIFS(Transactions!$H:$H,Transactions!$A:$A,">="&DATE(2026,4,1),Transactions!$A:$A,"<"&EDATE(DATE(2026,4,1),1),Transactions!$E:$E,"Expense",Transactions!$F:$F,"<>Cancelled") | F4: =SUMIFS(Transactions!$H:$H,Transactions!$A:$A,">="&DATE(2026,5,1),Transactions!$A:$A,"<"&EDATE(DATE(2026,5,1),1),Transactions!$E:$E,"Expense",Transactions!$F:$F,"<>Cancelled") | G4: =SUMIFS(Transactions!$H:$H,Transactions!$A:$A,">="&DATE(2026,6,1),Transactions!$A:$A,"<"&EDATE(DATE(2026,6,1),1),Transactions!$E:$E,"Expense",Transactions!$F:$F,"<>Cancelled") | H4: =SUMIFS(Transactions!$H:$H,Transactions!$A:$A,">="&DATE(2026,7,1),Transactions!$A:$A,"<"&EDATE(DATE(2026,7,1),1),Transactions!$E:$E,"Expense",Transactions!$F:$F,"<>Cancelled") | I4: =SUMIFS(Transactions!$H:$H,Transactions!$A:$A,">="&DATE(2026,8,1),Transactions!$A:$A,"<"&EDATE(DATE(2026,8,1),1),Transactions!$E:$E,"Expense",Transactions!$F:$F,"<>Cancelled") | J4: =SUMIFS(Transactions!$H:$H,Transactions!$A:$A,">="&DATE(2026,9,1),Transactions!$A:$A,"<"&EDATE(DATE(2026,9,1),1),Transactions!$E:$E,"Expense",Transactions!$F:$F,"<>Cancelled") | K4: =SUMIFS(Transactions!$H:$H,Transactions!$A:$A,">="&DATE(2026,10,1),Transactions!$A:$A,"<"&EDATE(DATE(2026,10,1),1),Transactions!$E:$E,"Expense",Transactions!$F:$F,"<>Cancelled") | L4: =SUMIFS(Transactions!$H:$H,Transactions!$A:$A,">="&DATE(2026,11,1),Transactions!$A:$A,"<"&EDATE(DATE(2026,11,1),1),Transactions!$E:$E,"Expense",Transactions!$F:$F,"<>Cancelled") | M4: =SUMIFS(Transactions!$H:$H,Transactions!$A:$A,">="&DATE(2026,12,1),Transactions!$A:$A,"<"&EDATE(DATE(2026,12,1),1),Transactions!$E:$E,"Expense",Transactions!$F:$F,"<>Cancelled") | N4: =SUM(B4:M4)
A5: Net Profit | B5: =B3-B4 | C5: =C3-C4 | D5: =D3-D4 | E5: =E3-E4 | F5: =F3-F4 | G5: =G3-G4 | H5: =H3-H4 | I5: =I3-I4 | ... M5: =M3-M4 | N5: =SUM(B5:M5)
A7: Net Margin | B7: =IFERROR(B5/B3,0) | C7: =IFERROR(C5/C3,0) | D7: =IFERROR(D5/D3,0) | E7: =IFERROR(E5/E3,0) | F7: =IFERROR(F5/F3,0) | G7: =IFERROR(G5/G3,0) | H7: =IFERROR(H5/H3,0) | I7: =IFERROR(I5/I3,0) | ... N7: =IFERROR(N5/N3,0)

Sheet Cash Flow & Forecast
A1: Cash Flow & Forecast
A2: Daily cash visibility and 90-day forward projection.
A3: =Settings!$B$11 | B3: =SUM(Accounts!$D$3:$D$100) | C3: =SUMIFS(Transactions!$H:$H,Transactions!$A:$A,A3,Transactions!$E:$E,"Income",Transactions!$F:$F,"<>Cancelled") | D3: =SUMIFS(Transactions!$H:$H,Transactions!$A:$A,A3,Transactions!$E:$E,"Expense",Transactions!$F:$F,"<>Cancelled") | E3: =C3-D3 | F3: =SUMIFS(Receivables!$G:$G,Receivables!$D:$D,A3,Receivables!$H:$H,"<>Paid") | G3: =SUMIFS(Payables!$G:$G,Payables!$D:$D,A3,Payables!$H:$H,"<>Paid") | H3: =F3-G3+(AVERAGE('Monthly Summary'!$D$3:$D$14)/30) | I3: =B3+H3 | J3: =MAX(0,Settings!$B$12-I3)
A4: =A3+1 | B4: =I3 | C4: =SUMIFS(Transactions!$H:$H,Transactions!$A:$A,A4,Transactions!$E:$E,"Income",Transactions!$F:$F,"<>Cancelled") | D4: =SUMIFS(Transactions!$H:$H,Transactions!$A:$A,A4,Transactions!$E:$E,"Expense",Transactions!$F:$F,"<>Cancelled") | E4: =C4-D4 | F4: =SUMIFS(Receivables!$G:$G,Receivables!$D:$D,A4,Receivables!$H:$H,"<>Paid") | G4: =SUMIFS(Payables!$G:$G,Payables!$D:$D,A4,Payables!$H:$H,"<>Paid") | H4: =F4-G4+(AVERAGE('Monthly Summary'!$D$3:$D$14)/30) | I4: =B4+H4 | J4: =MAX(0,Settings!$B$12-I4) | L4: Forecast KPIs
A5: =A4+1 | B5: =I4 | C5: =SUMIFS(Transactions!$H:$H,Transactions!$A:$A,A5,Transactions!$E:$E,"Income",Transactions!$F:$F,"<>Cancelled") | D5: =SUMIFS(Transactions!$H:$H,Transactions!$A:$A,A5,Transactions!$E:$E,"Expense",Transactions!$F:$F,"<>Cancelled") | E5: =C5-D5 | F5: =SUMIFS(Receivables!$G:$G,Receivables!$D:$D,A5,Receivables!$H:$H,"<>Paid") | G5: =SUMIFS(Payables!$G:$G,Payables!$D:$D,A5,Payables!$H:$H,"<>Paid") | H5: =F5-G5+(AVERAGE('Monthly Summary'!$D$3:$D$14)/30) | I5: =B5+H5 | J5: =MAX(0,Settings!$B$12-I5) | L5: Starting Cash | M5: =B3
A6: =A5+1 | B6: =I5 | C6: =SUMIFS(Transactions!$H:$H,Transactions!$A:$A,A6,Transactions!$E:$E,"Income",Transactions!$F:$F,"<>Cancelled") | D6: =SUMIFS(Transactions!$H:$H,Transactions!$A:$A,A6,Transactions!$E:$E,"Expense",Transactions!$F:$F,"<>Cancelled") | E6: =C6-D6 | F6: =SUMIFS(Receivables!$G:$G,Receivables!$D:$D,A6,Receivables!$H:$H,"<>Paid") | G6: =SUMIFS(Payables!$G:$G,Payables!$D:$D,A6,Payables!$H:$H,"<>Paid") | H6: =F6-G6+(AVERAGE('Monthly Summary'!$D$3:$D$14)/30) | I6: =B6+H6 | J6: =MAX(0,Settings!$B$12-I6) | L6: 90-Day Ending Cash | M6: =I93
A7: =A6+1 | B7: =I6 | C7: =SUMIFS(Transactions!$H:$H,Transactions!$A:$A,A7,Transactions!$E:$E,"Income",Transactions!$F:$F,"<>Cancelled") | D7: =SUMIFS(Transactions!$H:$H,Transactions!$A:$A,A7,Transactions!$E:$E,"Expense",Transactions!$F:$F,"<>Cancelled") | E7: =C7-D7 | F7: =SUMIFS(Receivables!$G:$G,Receivables!$D:$D,A7,Receivables!$H:$H,"<>Paid") | G7: =SUMIFS(Payables!$G:$G,Payables!$D:$D,A7,Payables!$H:$H,"<>Paid") | H7: =F7-G7+(AVERAGE('Monthly Summary'!$D$3:$D$14)/30) | I7: =B7+H7 | J7: =MAX(0,Settings!$B$12-I7) | L7: Lowest Cash | M7: =MIN(I3:I93)
A8: =A7+1 | B8: =I7 | C8: =SUMIFS(Transactions!$H:$H,Transactions!$A:$A,A8,Transactions!$E:$E,"Income",Transactions!$F:$F,"<>Cancelled") | D8: =SUMIFS(Transactions!$H:$H,Transactions!$A:$A,A8,Transactions!$E:$E,"Expense",Transactions!$F:$F,"<>Cancelled") | E8: =C8-D8 | F8: =SUMIFS(Receivables!$G:$G,Receivables!$D:$D,A8,Receivables!$H:$H,"<>Paid") | G8: =SUMIFS(Payables!$G:$G,Payables!$D:$D,A8,Payables!$H:$H,"<>Paid") | H8: =F8-G8+(AVERAGE('Monthly Summary'!$D$3:$D$14)/30) | I8: =B8+H8 | J8: =MAX(0,Settings!$B$12-I8) | L8: Lowest Cash Date | M8: =INDEX(A3:A93,MATCH(M7,I3:I93,0))
A9: =A8+1 | B9: =I8 | C9: =SUMIFS(Transactions!$H:$H,Transactions!$A:$A,A9,Transactions!$E:$E,"Income",Transactions!$F:$F,"<>Cancelled") | D9: =SUMIFS(Transactions!$H:$H,Transactions!$A:$A,A9,Transactions!$E:$E,"Expense",Transactions!$F:$F,"<>Cancelled") | E9: =C9-D9 | F9: =SUMIFS(Receivables!$G:$G,Receivables!$D:$D,A9,Receivables!$H:$H,"<>Paid") | G9: =SUMIFS(Payables!$G:$G,Payables!$D:$D,A9,Payables!$H:$H,"<>Paid") | H9: =F9-G9+(AVERAGE('Monthly Summary'!$D$3:$D$14)/30) | I9: =B9+H9 | J9: =MAX(0,Settings!$B$12-I9) | L9: Reserve Target | M9: =Settings!B12
A10: =A9+1 | B10: =I9 | C10: =SUMIFS(Transactions!$H:$H,Transactions!$A:$A,A10,Transactions!$E:$E,"Income",Transactions!$F:$F,"<>Cancelled") | D10: =SUMIFS(Transactions!$H:$H,Transactions!$A:$A,A10,Transactions!$E:$E,"Expense",Transactions!$F:$F,"<>Cancelled") | E10: =C10-D10 | F10: =SUMIFS(Receivables!$G:$G,Receivables!$D:$D,A10,Receivables!$H:$H,"<>Paid") | G10: =SUMIFS(Payables!$G:$G,Payables!$D:$D,A10,Payables!$H:$H,"<>Paid") | H10: =F10-G10+(AVERAGE('Monthly Summary'!$D$3:$D$14)/30) | I10: =B10+H10 | J10: =MAX(0,Settings!$B$12-I10) | L10: Days Below Reserve | M10: =COUNTIF(I3:I93,"<"&Settings!B12)
A11: =A10+1 | B11: =I10 | C11: =SUMIFS(Transactions!$H:$H,Transactions!$A:$A,A11,Transactions!$E:$E,"Income",Transactions!$F:$F,"<>Cancelled") | D11: =SUMIFS(Transactions!$H:$H,Transactions!$A:$A,A11,Transactions!$E:$E,"Expense",Transactions!$F:$F,"<>Cancelled") | E11: =C11-D11 | F11: =SUMIFS(Receivables!$G:$G,Receivables!$D:$D,A11,Receivables!$H:$H,"<>Paid") | G11: =SUMIFS(Payables!$G:$G,Payables!$D:$D,A11,Payables!$H:$H,"<>Paid") | H11: =F11-G11+(AVERAGE('Monthly Summary'!$D$3:$D$14)/30) | I11: =B11+H11 | J11: =MAX(0,Settings!$B$12-I11)
A12: =A11+1 | B12: =I11 | C12: =SUMIFS(Transactions!$H:$H,Transactions!$A:$A,A12,Transactions!$E:$E,"Income",Transactions!$F:$F,"<>Cancelled") | D12: =SUMIFS(Transactions!$H:$H,Transactions!$A:$A,A12,Transactions!$E:$E,"Expense",Transactions!$F:$F,"<>Cancelled") | E12: =C12-D12 | F12: =SUMIFS(Receivables!$G:$G,Receivables!$D:$D,A12,Receivables!$H:$H,"<>Paid") | G12: =SUMIFS(Payables!$G:$G,Payables!$D:$D,A12,Payables!$H:$H,"<>Paid") | H12: =F12-G12+(AVERAGE('Monthly Summary'!$D$3:$D$14)/30) | I12: =B12+H12 | J12: =MAX(0,Settings!$B$12-I12)
A13: =A12+1 | B13: =I12 | C13: =SUMIFS(Transactions!$H:$H,Transactions!$A:$A,A13,Transactions!$E:$E,"Income",Transactions!$F:$F,"<>Cancelled") | D13: =SUMIFS(Transactions!$H:$H,Transactions!$A:$A,A13,Transactions!$E:$E,"Expense",Transactions!$F:$F,"<>Cancelled") | E13: =C13-D13 | F13: =SUMIFS(Receivables!$G:$G,Receivables!$D:$D,A13,Receivables!$H:$H,"<>Paid") | G13: =SUMIFS(Payables!$G:$G,Payables!$D:$D,A13,Payables!$H:$H,"<>Paid") | H13: =F13-G13+(AVERAGE('Monthly Summary'!$D$3:$D$14)/30) | I13: =B13+H13 | J13: =MAX(0,Settings!$B$12-I13)
A14: =A13+1 | B14: =I13 | C14: =SUMIFS(Transactions!$H:$H,Transactions!$A:$A,A14,Transactions!$E:$E,"Income",Transactions!$F:$F,"<>Cancelled") | D14: =SUMIFS(Transactions!$H:$H,Transactions!$A:$A,A14,Transactions!$E:$E,"Expense",Transactions!$F:$F,"<>Cancelled") | E14: =C14-D14 | F14: =SUMIFS(Receivables!$G:$G,Receivables!$D:$D,A14,Receivables!$H:$H,"<>Paid") | G14: =SUMIFS(Payables!$G:$G,Payables!$D:$D,A14,Payables!$H:$H,"<>Paid") | H14: =F14-G14+(AVERAGE('Monthly Summary'!$D$3:$D$14)/30) | I14: =B14+H14 | J14: =MAX(0,Settings!$B$12-I14)
A15: =A14+1 | B15: =I14 | C15: =SUMIFS(Transactions!$H:$H,Transactions!$A:$A,A15,Transactions!$E:$E,"Income",Transactions!$F:$F,"<>Cancelled") | D15: =SUMIFS(Transactions!$H:$H,Transactions!$A:$A,A15,Transactions!$E:$E,"Expense",Transactions!$F:$F,"<>Cancelled") | E15: =C15-D15 | F15: =SUMIFS(Receivables!$G:$G,Receivables!$D:$D,A15,Receivables!$H:$H,"<>Paid") | G15: =SUMIFS(Payables!$G:$G,Payables!$D:$D,A15,Payables!$H:$H,"<>Paid") | H15: =F15-G15+(AVERAGE('Monthly Summary'!$D$3:$D$14)/30) | I15: =B15+H15 | J15: =MAX(0,Settings!$B$12-I15)
A16: =A15+1 | B16: =I15 | C16: =SUMIFS(Transactions!$H:$H,Transactions!$A:$A,A16,Transactions!$E:$E,"Income",Transactions!$F:$F,"<>Cancelled") | D16: =SUMIFS(Transactions!$H:$H,Transactions!$A:$A,A16,Transactions!$E:$E,"Expense",Transactions!$F:$F,"<>Cancelled") | E16: =C16-D16 | F16: =SUMIFS(Receivables!$G:$G,Receivables!$D:$D,A16,Receivables!$H:$H,"<>Paid") | G16: =SUMIFS(Payables!$G:$G,Payables!$D:$D,A16,Payables!$H:$H,"<>Paid") | H16: =F16-G16+(AVERAGE('Monthly Summary'!$D$3:$D$14)/30) | I16: =B16+H16 | J16: =MAX(0,Settings!$B$12-I16)
A17: =A16+1 | B17: =I16 | C17: =SUMIFS(Transactions!$H:$H,Transactions!$A:$A,A17,Transactions!$E:$E,"Income",Transactions!$F:$F,"<>Cancelled") | D17: =SUMIFS(Transactions!$H:$H,Transactions!$A:$A,A17,Transactions!$E:$E,"Expense",Transactions!$F:$F,"<>Cancelled") | E17: =C17-D17 | F17: =SUMIFS(Receivables!$G:$G,Receivables!$D:$D,A17,Receivables!$H:$H,"<>Paid") | G17: =SUMIFS(Payables!$G:$G,Payables!$D:$D,A17,Payables!$H:$H,"<>Paid") | H17: =F17-G17+(AVERAGE('Monthly Summary'!$D$3:$D$14)/30) | I17: =B17+H17 | J17: =MAX(0,Settings!$B$12-I17)
A18: =A17+1 | B18: =I17 | C18: =SUMIFS(Transactions!$H:$H,Transactions!$A:$A,A18,Transactions!$E:$E,"Income",Transactions!$F:$F,"<>Cancelled") | D18: =SUMIFS(Transactions!$H:$H,Transactions!$A:$A,A18,Transactions!$E:$E,"Expense",Transactions!$F:$F,"<>Cancelled") | E18: =C18-D18 | F18: =SUMIFS(Receivables!$G:$G,Receivables!$D:$D,A18,Receivables!$H:$H,"<>Paid") | G18: =SUMIFS(Payables!$G:$G,Payables!$D:$D,A18,Payables!$H:$H,"<>Paid") | H18: =F18-G18+(AVERAGE('Monthly Summary'!$D$3:$D$14)/30) | I18: =B18+H18 | J18: =MAX(0,Settings!$B$12-I18)
A19: =A18+1 | B19: =I18 | C19: =SUMIFS(Transactions!$H:$H,Transactions!$A:$A,A19,Transactions!$E:$E,"Income",Transactions!$F:$F,"<>Cancelled") | D19: =SUMIFS(Transactions!$H:$H,Transactions!$A:$A,A19,Transactions!$E:$E,"Expense",Transactions!$F:$F,"<>Cancelled") | E19: =C19-D19 | F19: =SUMIFS(Receivables!$G:$G,Receivables!$D:$D,A19,Receivables!$H:$H,"<>Paid") | G19: =SUMIFS(Payables!$G:$G,Payables!$D:$D,A19,Payables!$H:$H,"<>Paid") | H19: =F19-G19+(AVERAGE('Monthly Summary'!$D$3:$D$14)/30) | I19: =B19+H19 | J19: =MAX(0,Settings!$B$12-I19)
A20: =A19+1 | B20: =I19 | C20: =SUMIFS(Transactions!$H:$H,Transactions!$A:$A,A20,Transactions!$E:$E,"Income",Transactions!$F:$F,"<>Cancelled") | D20: =SUMIFS(Transactions!$H:$H,Transactions!$A:$A,A20,Transactions!$E:$E,"Expense",Transactions!$F:$F,"<>Cancelled") | E20: =C20-D20 | F20: =SUMIFS(Receivables!$G:$G,Receivables!$D:$D,A20,Receivables!$H:$H,"<>Paid") | G20: =SUMIFS(Payables!$G:$G,Payables!$D:$D,A20,Payables!$H:$H,"<>Paid") | H20: =F20-G20+(AVERAGE('Monthly Summary'!$D$3:$D$14)/30) | I20: =B20+H20 | J20: =MAX(0,Settings!$B$12-I20)
A21: =A20+1 | B21: =I20 | C21: =SUMIFS(Transactions!$H:$H,Transactions!$A:$A,A21,Transactions!$E:$E,"Income",Transactions!$F:$F,"<>Cancelled") | D21: =SUMIFS(Transactions!$H:$H,Transactions!$A:$A,A21,Transactions!$E:$E,"Expense",Transactions!$F:$F,"<>Cancelled") | E21: =C21-D21 | F21: =SUMIFS(Receivables!$G:$G,Receivables!$D:$D,A21,Receivables!$H:$H,"<>Paid") | G21: =SUMIFS(Payables!$G:$G,Payables!$D:$D,A21,Payables!$H:$H,"<>Paid") | H21: =F21-G21+(AVERAGE('Monthly Summary'!$D$3:$D$14)/30) | I21: =B21+H21 | J21: =MAX(0,Settings!$B$12-I21)
A22: =A21+1 | B22: =I21 | C22: =SUMIFS(Transactions!$H:$H,Transactions!$A:$A,A22,Transactions!$E:$E,"Income",Transactions!$F:$F,"<>Cancelled") | D22: =SUMIFS(Transactions!$H:$H,Transactions!$A:$A,A22,Transactions!$E:$E,"Expense",Transactions!$F:$F,"<>Cancelled") | E22: =C22-D22 | F22: =SUMIFS(Receivables!$G:$G,Receivables!$D:$D,A22,Receivables!$H:$H,"<>Paid") | G22: =SUMIFS(Payables!$G:$G,Payables!$D:$D,A22,Payables!$H:$H,"<>Paid") | H22: =F22-G22+(AVERAGE('Monthly Summary'!$D$3:$D$14)/30) | I22: =B22+H22 | J22: =MAX(0,Settings!$B$12-I22)
... A93: =A92+1 | B93: =I92 | C93: =SUMIFS(Transactions!$H:$H,Transactions!$A:$A,A93,Transactions!$E:$E,"Income",Transactions!$F:$F,"<>Cancelled") | D93: =SUMIFS(Transactions!$H:$H,Transactions!$A:$A,A93,Transactions!$E:$E,"Expense",Transactions!$F:$F,"<>Cancelled") | E93: =C93-D93 | F93: =SUMIFS(Receivables!$G:$G,Receivables!$D:$D,A93,Receivables!$H:$H,"<>Paid") | G93: =SUMIFS(Payables!$G:$G,Payables!$D:$D,A93,Payables!$H:$H,"<>Paid") | H93: =F93-G93+(AVERAGE('Monthly Summary'!$D$3:$D$14)/30) | I93: =B93+H93 | J93: =MAX(0,Settings!$B$12-I93)

Sheet Goals & KPIs
A1: Goals & KPIs
A2: Track revenue, margin, reserve, collections and profit targets.
A3: Monthly Revenue | B3: =Settings!B9 | C3: =SUMIFS(Transactions!$H:$H,Transactions!$E:$E,"Income",Transactions!$F:$F,"<>Cancelled") | D3: =MIN(1,IFERROR(C3/B3,0)) | E3: =IF(D3>=1,"On Track",IF(D3>=0.75,"Watch","Needs Attention")) | F3: Review weekly
A4: Net Margin | B4: =Settings!B10 | C4: =IFERROR((SUMIFS(Transactions!$H:$H,Transactions!$E:$E,"Income")-SUMIFS(Transactions!$H:$H,Transactions!$E:$E,"Expense"))/SUMIFS(Transactions!$H:$H,Transactions!$E:$E,"Income"),0) | D4: =MIN(1,IFERROR(C4/B4,0)) | E4: =IF(D4>=1,"On Track",IF(D4>=0.75,"Watch","Needs Attention")) | F4: Review weekly
A5: Cash Reserve | B5: =Settings!B12 | C5: =SUM(Accounts!D3:D100) | D5: =MIN(1,IFERROR(C5/B5,0)) | E5: =IF(D5>=1,"On Track",IF(D5>=0.75,"Watch","Needs Attention")) | F5: Review weekly
A6: Receivables Collected | B6: =SUM(Receivables!E3:E100) | C6: =SUM(Receivables!F3:F100) | D6: =MIN(1,IFERROR(C6/B6,0)) | E6: =IF(D6>=1,"On Track",IF(D6>=0.75,"Watch","Needs Attention")) | F6: Review weekly
A7: Budget Profit | B7: =SUM(Budget!D3:D14) | C7: =SUM('Monthly Summary'!D3:D14) | D7: =MIN(1,IFERROR(C7/B7,0)) | E7: =IF(D7>=1,"On Track",IF(D7>=0.75,"Watch","Needs Attention")) | F7: Review weekly

Sheet Financial Health
A1: Financial Health Score
A2: Management scorecard for profitability, liquidity, collections and forecast risk.
A3: Net Margin | B3: >= 20% | C3: =IFERROR('Monthly Summary'!D14/'Monthly Summary'!B14,0) | D3: =MIN(100,MAX(0,C3/Settings!B10*100)) | E3: =IF(D3>=80,"Healthy",IF(D3>=60,"Watch","Risk")) | F3: Profitability
A4: Expense Ratio | B4: <= 80% | C4: =IFERROR('Monthly Summary'!C14/'Monthly Summary'!B14,0) | D4: =MIN(100,MAX(0,(1-C4)/0.2*100)) | E4: =IF(D4>=80,"Healthy",IF(D4>=60,"Watch","Risk")) | F4: Cost control
A5: Cash Reserve | B5: Cash >= target | C5: =SUM(Accounts!D3:D100) | D5: =MIN(100,IFERROR(C5/Settings!B12*100,0)) | E5: =IF(D5>=80,"Healthy",IF(D5>=60,"Watch","Risk")) | F5: Liquidity
A6: Receivables Outstanding | B6: Lower is better | C6: =SUM(Receivables!G3:G100) | D6: =MAX(0,100-MIN(100,C6/Settings!B12*100)) | E6: =IF(D6>=80,"Healthy",IF(D6>=60,"Watch","Risk")) | F6: Collections
A7: Payables Outstanding | B7: Manage obligations | C7: =SUM(Payables!G3:G100) | D7: =MAX(0,100-MIN(100,C7/Settings!B12*100)) | E7: =IF(D7>=80,"Healthy",IF(D7>=60,"Watch","Risk")) | F7: Obligations
A8: Revenue vs Budget | B8: >= 100% | C8: =IFERROR(SUM('Monthly Summary'!B3:B14)/SUM('Monthly Summary'!F3:F14),0) | D8: =MIN(100,C8*100) | E8: =IF(D8>=80,"Healthy",IF(D8>=60,"Watch","Risk")) | F8: Growth
A9: Profit vs Budget | B9: >= 100% | C9: =IFERROR(SUM('Monthly Summary'!D3:D14)/SUM('Monthly Summary'!H3:H14),0) | D9: =MIN(100,C9*100) | E9: =IF(D9>=80,"Healthy",IF(D9>=60,"Watch","Risk")) | F9: Execution
A10: Cash Forecast | B10: No days below reserve | C10: FALSE | D10: =MAX(0,100-C10*5) | E10: =IF(D10>=80,"Healthy",IF(D10>=60,"Watch","Risk")) | F10: Forward risk
A13: Overall Financial Health Score | B13: =ROUND(AVERAGE(D3:D10),0) | C13: =IF(B13>=80,"HEALTHY",IF(B13>=60,"WATCH","ACTION REQUIRED"))
A15: Interpretation | B15: 80–100 Healthy | 60–79 Watch | Below 60 Action Required
